smume/__init__.py
smume/colors.py
smume/course_model.py
smume/curricula/_2024_25.py
smume/curricula/__init__.py
smume/curriculum.py
smume/flowchart_generator copy.py
smume/flowchart_generator.py
smume/generic_plan.py
smume/graph_builder.py
smume/img/courses_2014
smume/img/courses_2014.svg
smume/img/courses_2014_legend
smume/img/courses_2014_legend.svg
smume/img/courses_2015
smume/img/courses_2015.svg
smume/img/courses_2015_legend
smume/img/courses_2015_legend.svg
smume/img/courses_2016
smume/img/courses_2016.svg
smume/img/courses_2016_legend
smume/img/courses_2016_legend.svg
smume/img/courses_2017
smume/img/courses_2017.py
smume/img/courses_2017.svg
smume/img/courses_2017_legend
smume/img/courses_2017_legend.svg
smume/img/courses_2018
smume/img/courses_2018.svg
smume/img/courses_2018_legend
smume/img/courses_2018_legend.svg
smume/img/courses_2019
smume/img/courses_2019.svg
smume/img/courses_2019_legend
smume/img/courses_2019_legend.svg
smume/img/courses_2024
smume/img/courses_2024.svg
smume/img/courses_2024_legend
smume/img/courses_2024_legend.svg
smume/me_plan_document.py
smume/report.py
smume/requirements
smume/student_plan.py
smume/styles.py
smume/utils.py
smume-0.1.8.dist-info/METADATA
smume-0.1.8.dist-info/WHEEL
smume-0.1.8.dist-info/RECORD
