Metadata-Version: 2.1
Name: smume
Version: 0.1.8
Summary: A package for Saint Martin's University Mechanical Engineering students to create a custom flowchart for their academic plan.
Author: Rico Picone
Author-email: rpicone@stmartin.edu
Requires-Python: >=3.12,<4.0
Classifier: Programming Language :: Python :: 3
Classifier: Programming Language :: Python :: 3.12
Requires-Dist: beautifulsoup4 (>=4.13.4,<5.0.0)
Requires-Dist: graphviz (>=0.21,<0.22)
Requires-Dist: weasyprint (>=65.1,<66.0)
